{
	"info": {
		"_postman_id": "5dc0f329-bf4a-49b3-8907-91b8f44c3d9c",
		"name": "MyGroceryAPI",
		"schema": "https://schema.getpostman.com/json/collection/v2.1.0/collection.json",
		"_exporter_id": "28183194"
	},
	"item": [
		{
			"name": "Banner",
			"item": [
				{
					"name": "New Request",
					"request": {
						"method": "GET",
						"header": [],
						"url": {
							"raw": "http://localhost:1337/api/banners?populate=image",
							"protocol": "http",
							"host": [
								"localhost"
							],
							"port": "1337",
							"path": [
								"api",
								"banners"
							],
							"query": [
								{
									"key": "populate",
									"value": "image"
								}
							]
						}
					},
					"response": []
				}
			]
		},
		{
			"name": "Popular-Category",
			"item": [
				{
					"name": "New Request",
					"request": {
						"method": "GET",
						"header": [],
						"url": {
							"raw": "http://localhost:1337/api/popular-categories?populate=category, category.image&pagination[start]=0&pagination[limit]=5",
							"protocol": "http",
							"host": [
								"localhost"
							],
							"port": "1337",
							"path": [
								"api",
								"popular-categories"
							],
							"query": [
								{
									"key": "populate",
									"value": "category, category.image"
								},
								{
									"key": "pagination[start]",
									"value": "0"
								},
								{
									"key": "pagination[limit]",
									"value": "5"
								}
							]
						}
					},
					"response": []
				}
			]
		},
		{
			"name": "Popular-Product",
			"item": [
				{
					"name": "New Request",
					"request": {
						"method": "GET",
						"header": [],
						"url": {
							"raw": "http://localhost:1337/api/popular-products?populate=product,product.images",
							"protocol": "http",
							"host": [
								"localhost"
							],
							"port": "1337",
							"path": [
								"api",
								"popular-products"
							],
							"query": [
								{
									"key": "populate",
									"value": "product,product.images"
								}
							]
						}
					},
					"response": []
				}
			]
		},
		{
			"name": "Product",
			"item": [
				{
					"name": "New Request",
					"request": {
						"method": "GET",
						"header": [],
						"url": {
							"raw": "http://localhost:1337/api/products?populate=image,tags",
							"protocol": "http",
							"host": [
								"localhost"
							],
							"port": "1337",
							"path": [
								"api",
								"products"
							],
							"query": [
								{
									"key": "populate",
									"value": "image,tags"
								}
							]
						}
					},
					"response": []
				}
			]
		},
		{
			"name": "Category",
			"item": [
				{
					"name": "New Request",
					"request": {
						"method": "GET",
						"header": [],
						"url": {
							"raw": "http://localhost:1337/api/categories?populate=image",
							"protocol": "http",
							"host": [
								"localhost"
							],
							"port": "1337",
							"path": [
								"api",
								"categories"
							],
							"query": [
								{
									"key": "populate",
									"value": "image"
								}
							]
						}
					},
					"response": []
				}
			]
		},
		{
			"name": "Auth",
			"item": [
				{
					"name": "sign_in",
					"request": {
						"method": "POST",
						"header": [],
						"body": {
							"mode": "raw",
							"raw": "{\r\n    \"username\": \"sample1@gmail.com\",\r\n    \"email\": \"sample1@gmail.com\",\r\n    \"password\": \"pass@0123\"\r\n}",
							"options": {
								"raw": {
									"language": "json"
								}
							}
						},
						"url": {
							"raw": "http://localhost:1337/api/auth/local/register",
							"protocol": "http",
							"host": [
								"localhost"
							],
							"port": "1337",
							"path": [
								"api",
								"auth",
								"local",
								"register"
							]
						}
					},
					"response": []
				},
				{
					"name": "sign_in",
					"request": {
						"method": "POST",
						"header": [],
						"body": {
							"mode": "raw",
							"raw": "{\r\n    \"identifier\": \"sample1@gmail.com\",\r\n    \"password\": \"pass@0123\"\r\n}",
							"options": {
								"raw": {
									"language": "json"
								}
							}
						},
						"url": {
							"raw": "http://localhost:1337/api/auth/local",
							"protocol": "http",
							"host": [
								"localhost"
							],
							"port": "1337",
							"path": [
								"api",
								"auth",
								"local"
							]
						}
					},
					"response": []
				},
				{
					"name": "profileCreateMe",
					"request": {
						"auth": {
							"type": "bearer",
							"bearer": [
								{
									"key": "token",
									"value": "eyJhbGciOiJIUzI1NiIsInR5cCI6IkpXVCJ9.eyJpZCI6MiwiaWF0IjoxNjk3Nzg3OTM1LCJleHAiOjE3MDAzNzk5MzV9.MttAgjbVxjpG2KeY0hafznp5ZIRaPBS7mZ7ury1bW_o",
									"type": "string"
								}
							]
						},
						"method": "POST",
						"header": [],
						"body": {
							"mode": "raw",
							"raw": "{\r\n    \"fullName\": \"Aashu\"\r\n    \r\n}",
							"options": {
								"raw": {
									"language": "json"
								}
							}
						},
						"url": {
							"raw": "http://localhost:1337/api/profile/me",
							"protocol": "http",
							"host": [
								"localhost"
							],
							"port": "1337",
							"path": [
								"api",
								"profile",
								"me"
							]
						}
					},
					"response": []
				},
				{
					"name": "profileGetMe",
					"request": {
						"auth": {
							"type": "bearer",
							"bearer": [
								{
									"key": "token",
									"value": "eyJhbGciOiJIUzI1NiIsInR5cCI6IkpXVCJ9.eyJpZCI6MiwiaWF0IjoxNjk3Nzg3OTM1LCJleHAiOjE3MDAzNzk5MzV9.MttAgjbVxjpG2KeY0hafznp5ZIRaPBS7mZ7ury1bW_o",
									"type": "string"
								}
							]
						},
						"method": "GET",
						"header": [],
						"url": {
							"raw": "http://localhost:1337/api/profile/me",
							"protocol": "http",
							"host": [
								"localhost"
							],
							"port": "1337",
							"path": [
								"api",
								"profile",
								"me"
							]
						}
					},
					"response": []
				}
			]
		}
	]
}